awesom/__init__.py
awesom/datasets.py
awesom/defaults.py
awesom/exceptions.py
awesom/grid.py
awesom/neighbors.py
awesom/plot.py
awesom/py.typed
awesom/som.py
awesom/typing.py
awesom/utilities.py
awesom/weights.py
awesom-0.1.6.dist-info/LICENSE
awesom-0.1.6.dist-info/METADATA
awesom-0.1.6.dist-info/WHEEL
awesom-0.1.6.dist-info/RECORD
