Metadata-Version: 2.1
Name: awesom
Version: 0.1.6
Summary: Self-organizing map framework for Python
Home-page: https://github.com/Teagum/awesom
License: BSD-3-Clause
Author: Michael Blaß
Author-email: mblass@posteo.net
Requires-Python: >=3.10,<4.0
Classifier: Intended Audience :: Education
Classifier: Intended Audience :: Information Technology
Classifier: Intended Audience :: Science/Research
Classifier: License :: OSI Approved :: BSD License
Classifier: Operating System :: OS Independent
Classifier: Programming Language :: Python :: 3
Classifier: Programming Language :: Python :: 3.10
Classifier: Programming Language :: Python :: 3.11
Classifier: Programming Language :: Python :: 3.12
Classifier: Programming Language :: Python :: 3.13
Classifier: Programming Language :: Python :: 3 :: Only
Classifier: Programming Language :: Python :: Implementation :: CPython
Classifier: Topic :: Education
Classifier: Topic :: Scientific/Engineering
Classifier: Typing :: Typed
Requires-Dist: matplotlib (>=3.6.1,<4.0.0)
Requires-Dist: numpy (>=2.0.0,<3.0.0)
Requires-Dist: scipy (>=1.14.0,<2.0.0)
Requires-Dist: tox (>=4.9.0,<5.0.0)
